{"nodes": [{"id": "users_alessio_sites_personali_formulamanager_specs_templates_task_template_md", "label": "task-template.md", "file_type": "document", "source_file": "specs/templates/task-template.md", "source_location": "L1"}, {"id": "templates_task_template_template_task_canonico", "label": "Template task canonico", "file_type": "document", "source_file": "specs/templates/task-template.md", "source_location": "L1"}, {"id": "templates_task_template_header", "label": "Header", "file_type": "document", "source_file": "specs/templates/task-template.md", "source_location": "L11"}, {"id": "templates_task_template_sezioni_obbligatorie", "label": "Sezioni obbligatorie", "file_type": "document", "source_file": "specs/templates/task-template.md", "source_location": "L22"}, {"id": "templates_task_template_dipendenze", "label": "Dipendenze", "file_type": "document", "source_file": "specs/templates/task-template.md", "source_location": "L24"}, {"id": "templates_task_template_wave", "label": "Wave", "file_type": "document", "source_file": "specs/templates/task-template.md", "source_location": "L29"}, {"id": "templates_task_template_scope", "label": "Scope", "file_type": "document", "source_file": "specs/templates/task-template.md", "source_location": "L34"}, {"id": "templates_task_template_scenario_utente", "label": "Scenario utente", "file_type": "document", "source_file": "specs/templates/task-template.md", "source_location": "L39"}, {"id": "templates_task_template_deliverable_verificabile", "label": "Deliverable verificabile", "file_type": "document", "source_file": "specs/templates/task-template.md", "source_location": "L55"}, {"id": "templates_task_template_file_da_toccare", "label": "File da toccare", "file_type": "document", "source_file": "specs/templates/task-template.md", "source_location": "L73"}, {"id": "templates_task_template_definition_of_done", "label": "Definition of Done", "file_type": "document", "source_file": "specs/templates/task-template.md", "source_location": "L81"}, {"id": "templates_task_template_cosa_non_fare", "label": "Cosa NON fare", "file_type": "document", "source_file": "specs/templates/task-template.md", "source_location": "L101"}, {"id": "templates_task_template_riferimenti", "label": "Riferimenti", "file_type": "document", "source_file": "specs/templates/task-template.md", "source_location": "L111"}, {"id": "templates_task_template_sezioni_opzionali", "label": "Sezioni opzionali", "file_type": "document", "source_file": "specs/templates/task-template.md", "source_location": "L121"}, {"id": "templates_task_template_note_operative", "label": "Note operative", "file_type": "document", "source_file": "specs/templates/task-template.md", "source_location": "L123"}, {"id": "templates_task_template_edge_case", "label": "Edge case", "file_type": "document", "source_file": "specs/templates/task-template.md", "source_location": "L129"}, {"id": "templates_task_template_open_question", "label": "Open question", "file_type": "document", "source_file": "specs/templates/task-template.md", "source_location": "L135"}, {"id": "templates_task_template_test_manuali", "label": "Test manuali", "file_type": "document", "source_file": "specs/templates/task-template.md", "source_location": "L141"}, {"id": "templates_task_template_esempio_minimo_compilato", "label": "Esempio minimo compilato", "file_type": "document", "source_file": "specs/templates/task-template.md", "source_location": "L155"}], "edges": [{"source": "users_alessio_sites_personali_formulamanager_specs_templates_task_template_md", "target": "templates_task_template_template_task_canonico", "relation": "contains", "confidence": "EXTRACTED", "source_file": "specs/templates/task-template.md", "source_location": "L1", "weight": 1.0}, {"source": "templates_task_template_template_task_canonico", "target": "templates_task_template_header", "relation": "contains", "confidence": "EXTRACTED", "source_file": "specs/templates/task-template.md", "source_location": "L11", "weight": 1.0}, {"source": "templates_task_template_template_task_canonico", "target": "templates_task_template_sezioni_obbligatorie", "relation": "contains", "confidence": "EXTRACTED", "source_file": "specs/templates/task-template.md", "source_location": "L22", "weight": 1.0}, {"source": "templates_task_template_sezioni_obbligatorie", "target": "templates_task_template_dipendenze", "relation": "contains", "confidence": "EXTRACTED", "source_file": "specs/templates/task-template.md", "source_location": "L24", "weight": 1.0}, {"source": "templates_task_template_sezioni_obbligatorie", "target": "templates_task_template_wave", "relation": "contains", "confidence": "EXTRACTED", "source_file": "specs/templates/task-template.md", "source_location": "L29", "weight": 1.0}, {"source": "templates_task_template_sezioni_obbligatorie", "target": "templates_task_template_scope", "relation": "contains", "confidence": "EXTRACTED", "source_file": "specs/templates/task-template.md", "source_location": "L34", "weight": 1.0}, {"source": "templates_task_template_sezioni_obbligatorie", "target": "templates_task_template_scenario_utente", "relation": "contains", "confidence": "EXTRACTED", "source_file": "specs/templates/task-template.md", "source_location": "L39", "weight": 1.0}, {"source": "templates_task_template_sezioni_obbligatorie", "target": "templates_task_template_deliverable_verificabile", "relation": "contains", "confidence": "EXTRACTED", "source_file": "specs/templates/task-template.md", "source_location": "L55", "weight": 1.0}, {"source": "templates_task_template_sezioni_obbligatorie", "target": "templates_task_template_file_da_toccare", "relation": "contains", "confidence": "EXTRACTED", "source_file": "specs/templates/task-template.md", "source_location": "L73", "weight": 1.0}, {"source": "templates_task_template_sezioni_obbligatorie", "target": "templates_task_template_definition_of_done", "relation": "contains", "confidence": "EXTRACTED", "source_file": "specs/templates/task-template.md", "source_location": "L81", "weight": 1.0}, {"source": "templates_task_template_sezioni_obbligatorie", "target": "templates_task_template_cosa_non_fare", "relation": "contains", "confidence": "EXTRACTED", "source_file": "specs/templates/task-template.md", "source_location": "L101", "weight": 1.0}, {"source": "templates_task_template_sezioni_obbligatorie", "target": "templates_task_template_riferimenti", "relation": "contains", "confidence": "EXTRACTED", "source_file": "specs/templates/task-template.md", "source_location": "L111", "weight": 1.0}, {"source": "templates_task_template_template_task_canonico", "target": "templates_task_template_sezioni_opzionali", "relation": "contains", "confidence": "EXTRACTED", "source_file": "specs/templates/task-template.md", "source_location": "L121", "weight": 1.0}, {"source": "templates_task_template_sezioni_opzionali", "target": "templates_task_template_note_operative", "relation": "contains", "confidence": "EXTRACTED", "source_file": "specs/templates/task-template.md", "source_location": "L123", "weight": 1.0}, {"source": "templates_task_template_sezioni_opzionali", "target": "templates_task_template_edge_case", "relation": "contains", "confidence": "EXTRACTED", "source_file": "specs/templates/task-template.md", "source_location": "L129", "weight": 1.0}, {"source": "templates_task_template_sezioni_opzionali", "target": "templates_task_template_open_question", "relation": "contains", "confidence": "EXTRACTED", "source_file": "specs/templates/task-template.md", "source_location": "L135", "weight": 1.0}, {"source": "templates_task_template_sezioni_opzionali", "target": "templates_task_template_test_manuali", "relation": "contains", "confidence": "EXTRACTED", "source_file": "specs/templates/task-template.md", "source_location": "L141", "weight": 1.0}, {"source": "templates_task_template_template_task_canonico", "target": "templates_task_template_esempio_minimo_compilato", "relation": "contains", "confidence": "EXTRACTED", "source_file": "specs/templates/task-template.md", "source_location": "L155", "weight": 1.0}], "input_tokens": 0, "output_tokens": 0}